deepfeatx/__init__.py
deepfeatx/_nbdev.py
deepfeatx/image.py
deepfeatx-0.1.3.dist-info/LICENSE
deepfeatx-0.1.3.dist-info/METADATA
deepfeatx-0.1.3.dist-info/WHEEL
deepfeatx-0.1.3.dist-info/entry_points.txt
deepfeatx-0.1.3.dist-info/top_level.txt
deepfeatx-0.1.3.dist-info/RECORD
