Metadata-Version: 2.1
Name: deepfeatx
Version: 0.1.3
Summary: "Automatic Feature Extraction in Images and Texts using Transfer Learning"
Home-page: https://github.com/wittmannf/deepfeatx/tree/{branch}/
Author: Fernando M Wittmann
Author-email: fernando.wittmann@gmail.com
License: Apache Software License 2.0
Keywords: deep learning,transfer learning,feature extraction,bottleneck features
Platform: UNKNOWN
Classifier: Development Status :: 3 - Alpha
Classifier: Intended Audience :: Developers
Classifier: Natural Language :: English
Classifier: Programming Language :: Python :: 3.6
Classifier: Programming Language :: Python :: 3.7
Classifier: Programming Language :: Python :: 3.8
Classifier: License :: OSI Approved :: Apache Software License
Requires-Python: >=3.6
License-File: LICENSE
Requires-Dist: numpy
Requires-Dist: tensorflow (>=1.14.0)
Requires-Dist: torchvision (>=0.2.2)
Requires-Dist: requests
Requires-Dist: pandas
Requires-Dist: matplotlib
Requires-Dist: Pillow
Requires-Dist: scipy
Requires-Dist: scikit-learn
Requires-Dist: seaborn
